CHANGELOG.txt
LICENSE.txt
MANIFEST.in
README.rst
lgpl-2.1.txt
setup.py
doc/conf.py
doc/index.rst
doc/jekyll_fix.py
examples/deepzoom/deepzoom_multiserver.py
examples/deepzoom/deepzoom_server.py
examples/deepzoom/deepzoom_tile.py
examples/deepzoom/static/jquery.js
examples/deepzoom/static/openseadragon-scalebar.js
examples/deepzoom/static/openseadragon.js
examples/deepzoom/static/images/fullpage_grouphover.png
examples/deepzoom/static/images/fullpage_hover.png
examples/deepzoom/static/images/fullpage_pressed.png
examples/deepzoom/static/images/fullpage_rest.png
examples/deepzoom/static/images/home_grouphover.png
examples/deepzoom/static/images/home_hover.png
examples/deepzoom/static/images/home_pressed.png
examples/deepzoom/static/images/home_rest.png
examples/deepzoom/static/images/next_grouphover.png
examples/deepzoom/static/images/next_hover.png
examples/deepzoom/static/images/next_pressed.png
examples/deepzoom/static/images/next_rest.png
examples/deepzoom/static/images/previous_grouphover.png
examples/deepzoom/static/images/previous_hover.png
examples/deepzoom/static/images/previous_pressed.png
examples/deepzoom/static/images/previous_rest.png
examples/deepzoom/static/images/rotateleft_grouphover.png
examples/deepzoom/static/images/rotateleft_hover.png
examples/deepzoom/static/images/rotateleft_pressed.png
examples/deepzoom/static/images/rotateleft_rest.png
examples/deepzoom/static/images/rotateright_grouphover.png
examples/deepzoom/static/images/rotateright_hover.png
examples/deepzoom/static/images/rotateright_pressed.png
examples/deepzoom/static/images/rotateright_rest.png
examples/deepzoom/static/images/zoomin_grouphover.png
examples/deepzoom/static/images/zoomin_hover.png
examples/deepzoom/static/images/zoomin_pressed.png
examples/deepzoom/static/images/zoomin_rest.png
examples/deepzoom/static/images/zoomout_grouphover.png
examples/deepzoom/static/images/zoomout_hover.png
examples/deepzoom/static/images/zoomout_pressed.png
openslide_django.egg-info/PKG-INFO
openslide_django.egg-info/SOURCES.txt
openslide_django.egg-info/dependency_links.txt
openslide_django.egg-info/requires.txt
openslide_django.egg-info/top_level.txt
openslide_django.egg-info/zip-safe
